point_compiler/__init__.py
point_compiler/compiler.py
point_compiler-0.1.0.dist-info/licenses/LICENSE
point_compiler-0.1.0.dist-info/METADATA
point_compiler-0.1.0.dist-info/WHEEL
point_compiler-0.1.0.dist-info/top_level.txt
point_compiler-0.1.0.dist-info/RECORD
