Metadata-Version: 2.4
Name: point-compiler
Version: 0.1.0
Summary: A logic-based graph compiler for point-based computation
Author: Your Name
Author-email: you@example.com
Classifier: Programming Language :: Python :: 3
Classifier: License :: OSI Approved :: MIT License
Requires-Python: >=3.6
License-File: LICENSE
Dynamic: author
Dynamic: author-email
Dynamic: classifier
Dynamic: license-file
Dynamic: requires-python
Dynamic: summary
